oslodb_sqlalchemy_exceptions/__init__.py
oslodb_sqlalchemy_exceptions/exceptions.py
oslodb_sqlalchemy_exceptions/reflection.py
oslodb_sqlalchemy_exceptions/sqla_errors.py
oslodb_sqlalchemy_exceptions/warning.py
oslodb_sqlalchemy_exceptions-0.2.0.dist-info/WHEEL
oslodb_sqlalchemy_exceptions-0.2.0.dist-info/METADATA
oslodb_sqlalchemy_exceptions-0.2.0.dist-info/RECORD
